even_glasses/__init__.py
even_glasses/bluetooth_manager.py
even_glasses/command_logger.py
even_glasses/commands.py
even_glasses/models.py
even_glasses/notification_handlers.py
even_glasses/service_identifiers.py
even_glasses/utils.py
even_glasses-0.1.11.dist-info/LICENSE
even_glasses-0.1.11.dist-info/METADATA
even_glasses-0.1.11.dist-info/WHEEL
even_glasses-0.1.11.dist-info/top_level.txt
even_glasses-0.1.11.dist-info/RECORD
