Metadata-Version: 2.1
Name: even_glasses
Version: 0.1.11
Summary: A Python package for managing even-realities glasses devices via BLE.
Home-page: https://github.com/emingenc/even_glasses
Author: Emin Genc
Author-email: emingench@gmail.com
Classifier: Programming Language :: Python :: 3
Classifier: License :: OSI Approved :: GNU General Public License v3 (GPLv3)
Classifier: Operating System :: OS Independent
Requires-Python: >=3.9
License-File: LICENSE
Requires-Dist: bleak>=0.22.3
Requires-Dist: pydantic>=2.9.2
Requires-Dist: numpy>=1.26.4
Requires-Dist: numba>=0.60.0
